{"cid_44":{"meta":{"cid":"cid_44","fcon":11},"ctls":[{"d":[{"dp":39,"cid":"cid_43","mtx":[1,0,0,1,36,35]}]},{"d":[{"dp":39,"cid":"cid_43","mtx":[1,0,0,1,36,35]}]},{"d":[{"dp":39,"cid":"cid_43","mtx":[1,0,0,1,36,35]}]},{"d":[{"dp":39,"cid":"cid_43","mtx":[1,0,0,1,36,35]}]},{"d":[{"dp":39,"cid":"cid_43","mtx":[1,0,0,1,36,35]}]},{"d":[{"dp":39,"cid":"cid_43","mtx":[1,0,0,1,36,35]}]},{"d":[{"dp":39,"cid":"cid_43","mtx":[1,0,0,1,36,35]}]},{"d":[{"dp":39,"cid":"cid_43","mtx":[1,0,0,1,36,35]}]},{"d":[{"dp":39,"cid":"cid_43","mtx":[1,0,0,1,36,35]}]},{"d":[{"dp":39,"cid":"cid_43","mtx":[1,0,0,1,36,35]}]},{"d":[{"dp":39,"cid":"cid_43","mtx":[1,0,0,1,36,35]}],"act":[{"0":[129,[0,0]],"5":[6,[]],"6":[0,[]]}]}]}}